rk_core-0.1.14.dist-info/METADATA
rk_core-0.1.14.dist-info/WHEEL
rk_core/__init__.py
rk_core/rk_core.cp39-win_amd64.pyd
rk_core-0.1.14.dist-info/RECORD
